{
   "reblog-key" : "fMSGmVap",
   "photo-url-75" : "http://40.media.tumblr.com/tumblr_mcinbbguEw1qc8qobo1_75sq.jpg",
   "bookmarklet" : 0,
   "height" : 477,
   "tags" : [
      "how dare you",
      "HOW DARE YOU",
      "bill oreilly"
   ],
   "photo-url-250" : "http://40.media.tumblr.com/tumblr_mcinbbguEw1qc8qobo1_250.jpg",
   "type" : "photo",
   "from-feed-id" : 0,
   "photo-url-1280" : "http://36.media.tumblr.com/tumblr_mcinbbguEw1qc8qobo1_500.jpg",
   "date" : "Tue, 28 Oct 2014 16:39:57",
   "photo-caption" : "<p><a class=\"tumblr_blog\" href=\"http://prettyboyshyflizzy.tumblr.com/post/100580858194/internationalflycentre-blasianxbri-racism\">prettyboyshyflizzy</a>:</p>\n<blockquote>\n<p><a class=\"tumblr_blog\" href=\"http://internationalflycentre.tumblr.com/post/74066145549/blasianxbri-racism-in-its-purest-form-i\">internationalflycentre</a>:</p>\n<blockquote>\n<p><a class=\"tumblr_blog\" href=\"http://blasianxbri.tumblr.com/post/74063696558\">blasianxbri</a>:</p>\n<blockquote>\n<blockquote>\n<p>Racism in its PUREST form.</p>\n</blockquote>\n<p>I mean, let’s be real. Bill O’Reilly is ignorant as fuck. </p>\n</blockquote>\n<p>Fuckin prick</p>\n</blockquote>\n<p>how deep seeded your cism  gotta be to call a successful black man with a PHD a drug dealer then go on your show everyday and say racism doesnt exist</p>\n</blockquote>",
   "feed-item" : "",
   "width" : 933,
   "url" : "http://tumblr.ggvaidya.com/post/101206514869",
   "id" : "101206514869",
   "unix-timestamp" : 1414535997,
   "photos" : [
      {
         "photo-url-1280" : "http://36.media.tumblr.com/tumblr_mcinbbguEw1qc8qobo1_500.jpg",
         "width" : 933,
         "photo-url-500" : "http://36.media.tumblr.com/tumblr_mcinbbguEw1qc8qobo1_500.jpg",
         "photo-url-400" : "http://40.media.tumblr.com/tumblr_mcinbbguEw1qc8qobo1_400.jpg",
         "offset" : "o1",
         "height" : 477,
         "photo-url-75" : "http://40.media.tumblr.com/tumblr_mcinbbguEw1qc8qobo1_75sq.jpg",
         "photo-url-250" : "http://40.media.tumblr.com/tumblr_mcinbbguEw1qc8qobo1_250.jpg",
         "photo-url-100" : "http://40.media.tumblr.com/tumblr_mcinbbguEw1qc8qobo1_100.jpg",
         "caption" : ""
      },
      {
         "photo-url-250" : "http://40.media.tumblr.com/tumblr_mcinbbguEw1qc8qobo2_250.jpg",
         "photo-url-100" : "http://41.media.tumblr.com/tumblr_mcinbbguEw1qc8qobo2_100.jpg",
         "photo-url-75" : "http://40.media.tumblr.com/tumblr_mcinbbguEw1qc8qobo2_75sq.jpg",
         "height" : 477,
         "offset" : "o2",
         "caption" : "",
         "width" : 933,
         "photo-url-1280" : "http://40.media.tumblr.com/tumblr_mcinbbguEw1qc8qobo2_500.jpg",
         "photo-url-400" : "http://41.media.tumblr.com/tumblr_mcinbbguEw1qc8qobo2_400.jpg",
         "photo-url-500" : "http://40.media.tumblr.com/tumblr_mcinbbguEw1qc8qobo2_500.jpg"
      }
   ],
   "photo-url-100" : "http://40.media.tumblr.com/tumblr_mcinbbguEw1qc8qobo1_100.jpg",
   "photo-url-500" : "http://36.media.tumblr.com/tumblr_mcinbbguEw1qc8qobo1_500.jpg",
   "date-gmt" : "2014-10-28 22:39:57 GMT",
   "format" : "html",
   "photo-url-400" : "http://40.media.tumblr.com/tumblr_mcinbbguEw1qc8qobo1_400.jpg",
   "mobile" : 0,
   "slug" : "prettyboyshyflizzy-internationalflycentre",
   "url-with-slug" : "http://tumblr.ggvaidya.com/post/101206514869/prettyboyshyflizzy-internationalflycentre"
}

