{
   "date" : "Thu, 04 Dec 2014 00:16:44",
   "unix-timestamp" : 1417677404,
   "video-caption" : "<p>What a strange show.</p>",
   "tags" : [
      "twin peaks",
      "the red room",
      "the man from another place",
      "spoilers"
   ],
   "url-with-slug" : "http://tumblr.ggvaidya.com/post/104313181304/what-a-strange-show",
   "video-source" : "https://www.youtube.com/watch?v=qkhXHFnu99A",
   "mobile" : 0,
   "date-gmt" : "2014-12-04 07:16:44 GMT",
   "type" : "video",
   "feed-item" : "",
   "slug" : "what-a-strange-show",
   "format" : "html",
   "video-player-250" : "<iframe width=\"250\" height=\"140\" src=\"https://www.youtube.com/embed/qkhXHFnu99A?feature=oembed\" frameborder=\"0\" allowfullscreen></iframe>",
   "video-player" : "<iframe width=\"400\" height=\"225\" src=\"https://www.youtube.com/embed/qkhXHFnu99A?feature=oembed\" frameborder=\"0\" allowfullscreen></iframe>",
   "reblog-key" : "oN8iOTCc",
   "from-feed-id" : 0,
   "bookmarklet" : 0,
   "url" : "http://tumblr.ggvaidya.com/post/104313181304",
   "video-player-500" : "<iframe width=\"500\" height=\"281\" src=\"https://www.youtube.com/embed/qkhXHFnu99A?feature=oembed\" frameborder=\"0\" allowfullscreen></iframe>",
   "id" : "104313181304"
}

