{
   "date-gmt" : "2015-01-22 21:20:05 GMT",
   "bookmarklet" : 0,
   "mobile" : 0,
   "width" : "600",
   "slug" : "addelburgh-incognito",
   "reblog-key" : "A9CXci3M",
   "from-feed-id" : 0,
   "photo-url-250" : "http://40.media.tumblr.com/df76d3c8944b36ff84798a58a2b71936/tumblr_n0yu50r5Y31qhwlspo1_250.jpg",
   "format" : "html",
   "height" : "450",
   "photo-url-75" : "http://40.media.tumblr.com/df76d3c8944b36ff84798a58a2b71936/tumblr_n0yu50r5Y31qhwlspo1_75sq.jpg",
   "photo-url-500" : "http://41.media.tumblr.com/df76d3c8944b36ff84798a58a2b71936/tumblr_n0yu50r5Y31qhwlspo1_500.jpg",
   "photo-url-400" : "http://40.media.tumblr.com/df76d3c8944b36ff84798a58a2b71936/tumblr_n0yu50r5Y31qhwlspo1_400.jpg",
   "type" : "photo",
   "tags" : [
      "they won't see me here",
      "cat"
   ],
   "photo-url-100" : "http://41.media.tumblr.com/df76d3c8944b36ff84798a58a2b71936/tumblr_n0yu50r5Y31qhwlspo1_100.jpg",
   "unix-timestamp" : 1421961605,
   "photo-caption" : "<p><a class=\"tumblr_blog\" href=\"http://addelburgh.tumblr.com/post/76593793097/incognito\">addelburgh</a>:</p>\n<blockquote>\n<p>incognito</p>\n</blockquote>",
   "url" : "http://tumblr.ggvaidya.com/post/108853822660",
   "url-with-slug" : "http://tumblr.ggvaidya.com/post/108853822660/addelburgh-incognito",
   "photos" : [],
   "id" : "108853822660",
   "feed-item" : "",
   "date" : "Thu, 22 Jan 2015 14:20:05",
   "photo-url-1280" : "http://41.media.tumblr.com/df76d3c8944b36ff84798a58a2b71936/tumblr_n0yu50r5Y31qhwlspo1_1280.jpg"
}

