{
   "regular-title" : null,
   "unix-timestamp" : 1444711767,
   "id" : "131070721799",
   "slug" : "man-am-i-stressed-i-havent-been-this-stressed-in",
   "url-with-slug" : "http://tumblr.ggvaidya.com/post/131070721799/man-am-i-stressed-i-havent-been-this-stressed-in",
   "mobile" : 0,
   "regular-body" : "<p>Man am I stressed I haven&rsquo;t been this stressed in a while the good news is that by next Monday everything should be peachy but until then UNTIL THEN stressssss</p>",
   "format" : "html",
   "date-gmt" : "2015-10-13 04:49:27 GMT",
   "tags" : [
      "personal"
   ],
   "bookmarklet" : 0,
   "reblog-key" : "DGGSFEnG",
   "url" : "http://tumblr.ggvaidya.com/post/131070721799",
   "date" : "Mon, 12 Oct 2015 22:49:27",
   "feed-item" : "",
   "type" : "regular",
   "from-feed-id" : 0
}

