{
   "bookmarklet" : 0,
   "date" : "Sat, 31 Oct 2015 14:20:08",
   "date-gmt" : "2015-10-31 20:20:08 GMT",
   "feed-item" : "",
   "format" : "html",
   "from-feed-id" : 0,
   "height" : 480,
   "id" : "132290403018",
   "mobile" : 0,
   "photo-caption" : "<p><a class=\"tumblr_blog\" href=\"http://typhlonectes.tumblr.com/post/126854150548\">typhlonectes</a>:</p>\n<blockquote>\n<h2>\n<b>Pronghorn</b> (<i>Antilocapra americana</i>)<br/></h2>\n<p>Though\n their genus name, Antilocapra, means “antelope goat”, pronghorns are \nneither. The difference is in the antlers. Those of deer are shed every \nyear; those of antelope and goats never are. Pronghorns shed theirs \nannually, but only the outer layer, which is made up of keratin, like \nyour hair. <br/></p>\n<p>Pronghorns are the fastest land mammal of the Americas, \nsprinting at speeds of up to 55 mph (88 km/h). They\n are built for running, with a light bone structure and even hollow hair\n to make them lighter; it is hypothesized that their speed evolved to \nescape the now-extinct American cheetah, since no living North American \npredator can keep up with them. Their sprint is one of 13 distinct gaits\n they exhibit. <br/></p>\n<p>Pronghorns come together in the winter, forming mixed-sex\n herds; in the summer the sexes split up, with adult females and their \nyoung forming small herds, young bachelor males grouping together, and \nadult males living independently.<br/><br/><i>photo by Rick Cameron (rickcameron) on Flickr</i></p>\n<p>(via: <a href=\"https://www.facebook.com/pages/Peterson-Field-Guides/109873205706858?fref=photo\">Peterson Field Guides</a>)<br/></p>\n</blockquote>",
   "photo-link-url" : "https://www.facebook.com/109873205706858/photos/a.113930988634413.13798.109873205706858/1108417459185756/?type=1",
   "photo-url-100" : "http://40.media.tumblr.com/79cf8c2ea33500c7937561f016efc0db/tumblr_nt70kmD0eI1usv7xpo1_100.jpg",
   "photo-url-1280" : "http://40.media.tumblr.com/79cf8c2ea33500c7937561f016efc0db/tumblr_nt70kmD0eI1usv7xpo1_1280.jpg",
   "photo-url-250" : "http://41.media.tumblr.com/79cf8c2ea33500c7937561f016efc0db/tumblr_nt70kmD0eI1usv7xpo1_250.jpg",
   "photo-url-400" : "http://41.media.tumblr.com/79cf8c2ea33500c7937561f016efc0db/tumblr_nt70kmD0eI1usv7xpo1_400.jpg",
   "photo-url-500" : "http://40.media.tumblr.com/79cf8c2ea33500c7937561f016efc0db/tumblr_nt70kmD0eI1usv7xpo1_500.jpg",
   "photo-url-75" : "http://40.media.tumblr.com/79cf8c2ea33500c7937561f016efc0db/tumblr_nt70kmD0eI1usv7xpo1_75sq.jpg",
   "photos" : [],
   "reblog-key" : "PVF8dHxm",
   "slug" : "typhlonectes-pronghorn-antilocapra-americana",
   "tags" : [
      "we just saw some right now",
      "it was awesome"
   ],
   "type" : "photo",
   "unix-timestamp" : 1446322808,
   "url" : "http://tumblr.ggvaidya.com/post/132290403018",
   "url-with-slug" : "http://tumblr.ggvaidya.com/post/132290403018/typhlonectes-pronghorn-antilocapra-americana",
   "width" : 720
}

