{
   "bookmarklet" : 0,
   "date" : "Sun, 13 Mar 2016 15:40:32",
   "date-gmt" : "2016-03-13 21:40:32 GMT",
   "feed-item" : "",
   "format" : "html",
   "from-feed-id" : 0,
   "id" : "140991986856",
   "mobile" : 0,
   "quote-source" : "<p>immunology professor this week (via <a href=\"http://hyacinth-willow.tumblr.com/\" class=\"tumblr_blog\">hyacinth-willow</a>)</p><p>I mean, a fever is basically your immune system going, “LET’S SEE WHO BURNS FIRST, MOTHERFUCKER.”</p><p>(via <a href=\"http://thebastardofgloucester.tumblr.com/\" class=\"tumblr_blog\">thebastardofgloucester</a>)</p><p>#<a href=\"http://overtonesofreality.tumblr.com/tagged/also-most-deadly-illnesses-are-only-deadly-because-your-immune-system-is-trying-to-help\">ALSO MOST DEADLY ILLNESSES ARE ONLY DEADLY BECAUSE YOUR IMMUNE SYSTEM IS TRYING TO HELP</a></p><p>(via <a href=\"http://fightthecoldwithspices.tumblr.com/\" class=\"tumblr_blog\">fightthecoldwithspices</a>)</p>",
   "quote-text" : "as you know, the immune system walks a fine line between being absolutely useless and killing you",
   "reblog-key" : "bxPTxhK6",
   "slug" : "as-you-know-the-immune-system-walks-a-fine-line",
   "tags" : [
      "sigh",
      "my T-lymphocytes and me"
   ],
   "type" : "quote",
   "unix-timestamp" : 1457905232,
   "url" : "http://tumblr.ggvaidya.com/post/140991986856",
   "url-with-slug" : "http://tumblr.ggvaidya.com/post/140991986856/as-you-know-the-immune-system-walks-a-fine-line"
}

