{
   "bookmarklet" : 0,
   "photo-url-250" : "http://36.media.tumblr.com/75026982eb88986ad53a7d68bf810c39/tumblr_mguh5uhkxo1rss3xqo1_250.jpg",
   "slug" : "chain-of-prospit-no-you-dont-understand-these",
   "photo-url-500" : "http://41.media.tumblr.com/75026982eb88986ad53a7d68bf810c39/tumblr_mguh5uhkxo1rss3xqo1_500.jpg",
   "reblog-key" : "cT1Elhpw",
   "format" : "html",
   "unix-timestamp" : 1360611616,
   "date" : "Mon, 11 Feb 2013 12:40:16",
   "url-with-slug" : "http://tumblr.ggvaidya.com/post/42859010845/chain-of-prospit-no-you-dont-understand-these",
   "feed-item" : "",
   "from-feed-id" : 0,
   "width" : "1280",
   "date-gmt" : "2013-02-11 19:40:16 GMT",
   "id" : "42859010845",
   "mobile" : 0,
   "photo-url-400" : "http://41.media.tumblr.com/75026982eb88986ad53a7d68bf810c39/tumblr_mguh5uhkxo1rss3xqo1_400.jpg",
   "photo-url-75" : "http://40.media.tumblr.com/75026982eb88986ad53a7d68bf810c39/tumblr_mguh5uhkxo1rss3xqo1_75sq.jpg",
   "url" : "http://tumblr.ggvaidya.com/post/42859010845",
   "photo-url-1280" : "http://41.media.tumblr.com/75026982eb88986ad53a7d68bf810c39/tumblr_mguh5uhkxo1rss3xqo1_500.jpg",
   "photos" : [],
   "photo-caption" : "<p><a class=\"tumblr_blog\" href=\"http://chain-of-prospit.tumblr.com/post/40892195474/no-you-dont-understand-these-are-two-separate\">chain-of-prospit</a>:</p>\n<blockquote>\n<p>no you dont understand</p>\n<p>these are two separate toys that we found at the thrift store today okay</p>\n<p>and we found out that they fit like this and it was beautiful</p>\n<p>and then we were going up to the cashier to get our things and realized they were still like that and were separating them so that we could each purchase the one we had found and</p>\n<p>the cashier</p>\n<p>looked</p>\n<p>so confused and„, distressed and horrified omg</p>\n<p>the look on his face was like we had taken his soul and run it through a blenderim</p>\n<p>i tried to fix it omg i was just like</p>\n<p>“……………………..he was just…. resting”</p>\n<p>but i dont think anything can make up for the trauma we caused.</p>\n</blockquote>\n\n<p>Hmm.</p>",
   "photo-url-100" : "http://36.media.tumblr.com/75026982eb88986ad53a7d68bf810c39/tumblr_mguh5uhkxo1rss3xqo1_100.jpg",
   "type" : "photo",
   "height" : "960"
}

