{
   "bookmarklet" : 0,
   "date" : "Thu, 14 Feb 2013 00:41:25",
   "date-gmt" : "2013-02-14 05:41:25 GMT",
   "feed-item" : "",
   "format" : "html",
   "from-feed-id" : 0,
   "id" : "43060992415",
   "is-submission" : false,
   "mobile" : 0,
   "reblog-key" : "SeHGUqeB",
   "regular-body" : "<p><a href=\"http://betterhabitsblog.tumblr.com/post/43059543944/tell-someone-you-love-that-you-love-them-and-two\" class=\"tumblr_blog\">betterhabitsblog</a>:</p>\n\n<blockquote><p>Tell someone you love that you love them, and two things about them that you appreciate.</p></blockquote>\n\n<p>This is way beyond me this week, but maybe someday.</p>",
   "regular-title" : null,
   "slug" : "betterhabitsblog-tell-someone-you-love-that-you",
   "type" : "regular",
   "unix-timestamp" : 1360820485,
   "url" : "http://tumblr.ggvaidya.com/post/43060992415",
   "url-with-slug" : "http://tumblr.ggvaidya.com/post/43060992415/betterhabitsblog-tell-someone-you-love-that-you"
}

