{
   "date" : "Fri, 17 May 2013 15:16:04",
   "format" : "html",
   "slug" : "teenagesophiebennett-you-know-parents-make-such",
   "url-with-slug" : "http://tumblr.ggvaidya.com/post/50676006281/teenagesophiebennett-you-know-parents-make-such",
   "reblog-key" : "bC9TLfmq",
   "bookmarklet" : 0,
   "unix-timestamp" : 1368825364,
   "from-feed-id" : 0,
   "url" : "http://tumblr.ggvaidya.com/post/50676006281",
   "regular-title" : null,
   "type" : "regular",
   "regular-body" : "<p><a class=\"tumblr_blog\" href=\"http://teenagesophiebennett.tumblr.com/post/43819639365/you-know-parents-make-such-a-big-deal-about\">teenagesophiebennett</a>:</p>\n<blockquote>\n<p>you know parents make such a big deal about explaining homosexuality to their children but when I was a kid I watched a show where one of the villains was a satanic cross-dressing lobster and never once questioned it</p>\n<p><img alt=\"image\" src=\"http://media.tumblr.com/a734149e831e55f7e86a65766d0b7db2/tumblr_inline_miornqqGI41qz4rgp.gif\"/></p>\n</blockquote>",
   "date-gmt" : "2013-05-17 21:16:04 GMT",
   "feed-item" : "",
   "id" : "50676006281",
   "mobile" : 0,
   "tags" : [
      "him",
      "The Powerpuff Girls"
   ]
}

