{
   "date-gmt" : "2013-08-25 17:26:21 GMT",
   "tags" : [
      "can't say we haven't been warned",
      "george r r martin",
      "game of thrones"
   ],
   "quote-text" : "No one will be alive by the last book. In fact, they all die in the fifth. The sixth book will be just a thousand-page description of snow blowing across the graves.",
   "unix-timestamp" : 1377451581,
   "mobile" : 0,
   "url" : "http://tumblr.ggvaidya.com/post/59313165052",
   "feed-item" : "",
   "type" : "quote",
   "reblog-key" : "jto3re1S",
   "date" : "Sun, 25 Aug 2013 11:26:21",
   "format" : "html",
   "url-with-slug" : "http://tumblr.ggvaidya.com/post/59313165052/no-one-will-be-alive-by-the-last-book-in-fact",
   "quote-source" : "George R.R. Martin <br/><em><sub>(when asked if he was going to let any Game of Thrones/Song of Ice and Fire characters live)</sub></em>",
   "bookmarklet" : 0,
   "id" : "59313165052",
   "from-feed-id" : 0,
   "slug" : "no-one-will-be-alive-by-the-last-book-in-fact"
}

