{
   "slug" : "orions-up",
   "date" : "Sat, 09 Nov 2013 22:20:35",
   "url-with-slug" : "http://tumblr.ggvaidya.com/post/66540634863/orions-up",
   "date-gmt" : "2013-11-10 05:20:35 GMT",
   "regular-body" : "<p>Orion&rsquo;s up.</p>",
   "id" : "66540634863",
   "format" : "html",
   "url" : "http://tumblr.ggvaidya.com/post/66540634863",
   "from-feed-id" : 0,
   "type" : "regular",
   "unix-timestamp" : 1384060835,
   "feed-item" : "",
   "reblog-key" : "IvIRcdqR",
   "regular-title" : null,
   "tags" : [
      "life",
      "orion",
      "constellation",
      "stars",
      "reassuring",
      "scary",
      "disappointing"
   ],
   "mobile" : 0,
   "bookmarklet" : 0
}

