{
   "bookmarklet" : 0,
   "date" : "Mon, 02 Dec 2013 01:33:03",
   "date-gmt" : "2013-12-02 06:33:03 GMT",
   "feed-item" : "",
   "format" : "html",
   "from-feed-id" : 0,
   "height" : 694,
   "id" : "68759681471",
   "is-submission" : false,
   "like-button" : "<div class=\"like_button\" data-post-id=\"68759681471\" data-blog-name=\"mrvaidya\" id=\"like_button_68759681471\"><iframe id=\"like_iframe_68759681471\" src=\"http://assets.tumblr.com/assets/html/like_iframe.html?_v=9c1e0782724156703eb4f7ba79dbe203#name=mrvaidya&amp;post_id=68759681471&amp;color=black&amp;rk=M8vQxOpi&amp;root_id=67109862891\" scrolling=\"no\" width=\"20\" height=\"20\" frameborder=\"0\" class=\"like_toggle\" allowTransparency=\"true\" name=\"like_iframe_68759681471\"></iframe></div>",
   "mobile" : 0,
   "photo-caption" : "<p><a class=\"tumblr_blog\" href=\"http://mica-low.tumblr.com/post/67109862891/saguaro-cacti-in-bloom-with-the-nectar-feeding\">mica-low</a>:</p>\n<blockquote>\n<p>Saguaro cacti in bloom with the nectar-feeding Great Long-Nosed Bat (<em>Leptonycteris nivalis</em>). Done for a backlighting assignment in watercolor for the illustrator. </p>\n</blockquote>\n\n<p>This is lovely, but I can&rsquo;t not see the Welcome to Night Value colour scheme.</p>",
   "photo-url-100" : "http://68.media.tumblr.com/ccc45e6ccaf049cdf3bef420a1d4aabf/tumblr_mwc1qimAYz1rc1s3uo2_100.jpg",
   "photo-url-1280" : "http://68.media.tumblr.com/ccc45e6ccaf049cdf3bef420a1d4aabf/tumblr_mwc1qimAYz1rc1s3uo2_1280.jpg",
   "photo-url-250" : "http://68.media.tumblr.com/ccc45e6ccaf049cdf3bef420a1d4aabf/tumblr_mwc1qimAYz1rc1s3uo2_250.jpg",
   "photo-url-400" : "http://68.media.tumblr.com/ccc45e6ccaf049cdf3bef420a1d4aabf/tumblr_mwc1qimAYz1rc1s3uo2_400.jpg",
   "photo-url-500" : "http://68.media.tumblr.com/ccc45e6ccaf049cdf3bef420a1d4aabf/tumblr_mwc1qimAYz1rc1s3uo2_500.jpg",
   "photo-url-75" : "http://68.media.tumblr.com/ccc45e6ccaf049cdf3bef420a1d4aabf/tumblr_mwc1qimAYz1rc1s3uo2_75sq.jpg",
   "photos" : [
      {
         "caption" : "",
         "height" : 694,
         "offset" : "o2",
         "photo-url-100" : "http://68.media.tumblr.com/ccc45e6ccaf049cdf3bef420a1d4aabf/tumblr_mwc1qimAYz1rc1s3uo2_100.jpg",
         "photo-url-1280" : "http://68.media.tumblr.com/ccc45e6ccaf049cdf3bef420a1d4aabf/tumblr_mwc1qimAYz1rc1s3uo2_1280.jpg",
         "photo-url-250" : "http://68.media.tumblr.com/ccc45e6ccaf049cdf3bef420a1d4aabf/tumblr_mwc1qimAYz1rc1s3uo2_250.jpg",
         "photo-url-400" : "http://68.media.tumblr.com/ccc45e6ccaf049cdf3bef420a1d4aabf/tumblr_mwc1qimAYz1rc1s3uo2_400.jpg",
         "photo-url-500" : "http://68.media.tumblr.com/ccc45e6ccaf049cdf3bef420a1d4aabf/tumblr_mwc1qimAYz1rc1s3uo2_500.jpg",
         "photo-url-75" : "http://68.media.tumblr.com/ccc45e6ccaf049cdf3bef420a1d4aabf/tumblr_mwc1qimAYz1rc1s3uo2_75sq.jpg",
         "width" : 900
      },
      {
         "caption" : "",
         "height" : 6,
         "offset" : "o1",
         "photo-url-100" : "http://68.media.tumblr.com/5e7e74240172f58b9509ce2360867534/tumblr_mwc1qimAYz1rc1s3uo1_100.png",
         "photo-url-1280" : "http://68.media.tumblr.com/5e7e74240172f58b9509ce2360867534/tumblr_mwc1qimAYz1rc1s3uo1_500.png",
         "photo-url-250" : "http://68.media.tumblr.com/5e7e74240172f58b9509ce2360867534/tumblr_mwc1qimAYz1rc1s3uo1_250.png",
         "photo-url-400" : "http://68.media.tumblr.com/5e7e74240172f58b9509ce2360867534/tumblr_mwc1qimAYz1rc1s3uo1_400.png",
         "photo-url-500" : "http://68.media.tumblr.com/5e7e74240172f58b9509ce2360867534/tumblr_mwc1qimAYz1rc1s3uo1_500.png",
         "photo-url-75" : "http://68.media.tumblr.com/5e7e74240172f58b9509ce2360867534/tumblr_mwc1qimAYz1rc1s3uo1_75sq.png",
         "width" : 500
      }
   ],
   "reblog-button" : "<a href=\"https://www.tumblr.com/reblog/68759681471/M8vQxOpi\" class=\"reblog_button\"style=\"display: block;width:20px;height:20px;\"><svg width=\"100%\" height=\"100%\" viewBox=\"0 0 21 21\" xmlns=\"http://www.w3.org/2000/svg\" xmlns:xlink=\"http://www.w3.org/1999/xlink\" fill=\"#000\"><path d=\"M5.01092527,5.99908429 L16.0088498,5.99908429 L16.136,9.508 L20.836,4.752 L16.136,0.083 L16.1360004,3.01110845 L2.09985349,3.01110845 C1.50585349,3.01110845 0.979248041,3.44726568 0.979248041,4.45007306 L0.979248041,10.9999998 L3.98376463,8.30993634 L3.98376463,6.89801007 C3.98376463,6.20867902 4.71892527,5.99908429 5.01092527,5.99908429 Z\"></path><path d=\"M17.1420002,13.2800293 C17.1420002,13.5720293 17.022957,14.0490723 16.730957,14.0490723 L4.92919922,14.0490723 L4.92919922,11 L0.5,15.806 L4.92919922,20.5103758 L5.00469971,16.9990234 L18.9700928,16.9990234 C19.5640928,16.9990234 19.9453125,16.4010001 19.9453125,15.8060001 L19.9453125,9.5324707 L17.142,12.203\"></path></svg></a>",
   "reblog-key" : "M8vQxOpi",
   "slug" : "mica-low-saguaro-cacti-in-bloom-with-the",
   "tags" : [
      "wtnv",
      "desert"
   ],
   "type" : "photo",
   "unix-timestamp" : 1385965983,
   "url" : "http://tumblr.ggvaidya.com/post/68759681471",
   "url-with-slug" : "http://tumblr.ggvaidya.com/post/68759681471/mica-low-saguaro-cacti-in-bloom-with-the",
   "width" : 900
}

