{
   "date" : "Thu, 23 Jan 2014 22:20:21",
   "url-with-slug" : "http://tumblr.ggvaidya.com/post/74357748924/literally-sparkling-garbage-bins-what",
   "video-player" : "<iframe src=\"http://www.tumblr.com/video/mrvaidya/74357748924/400\" id=\"tumblr_video_iframe_74357748924\" class=\"tumblr_video_iframe\" width=\"400\" height=\"225\" style=\"display:block;background-color:transparent;overflow:hidden;\" allowTransparency=\"true\" frameborder=\"0\" scrolling=\"no\" webkitAllowFullScreen mozallowfullscreen allowFullScreen></iframe>",
   "date-gmt" : "2014-01-24 05:20:21 GMT",
   "mobile" : 0,
   "video-player-500" : "<iframe src=\"http://www.tumblr.com/video/mrvaidya/74357748924/500\" id=\"tumblr_video_iframe_74357748924\" class=\"tumblr_video_iframe\" width=\"500\" height=\"281\" style=\"display:block;background-color:transparent;overflow:hidden;\" allowTransparency=\"true\" frameborder=\"0\" scrolling=\"no\" webkitAllowFullScreen mozallowfullscreen allowFullScreen></iframe>",
   "slug" : "literally-sparkling-garbage-bins-what",
   "url" : "http://tumblr.ggvaidya.com/post/74357748924",
   "id" : "74357748924",
   "video-player-250" : "<iframe src=\"http://www.tumblr.com/video/mrvaidya/74357748924/250\" id=\"tumblr_video_iframe_74357748924\" class=\"tumblr_video_iframe\" width=\"250\" height=\"141\" style=\"display:block;background-color:transparent;overflow:hidden;\" allowTransparency=\"true\" frameborder=\"0\" scrolling=\"no\" webkitAllowFullScreen mozallowfullscreen allowFullScreen></iframe>",
   "from-feed-id" : 0,
   "bookmarklet" : 0,
   "feed-item" : "",
   "reblog-key" : "Jh7lyNYB",
   "tags" : [
      "snow"
   ],
   "video-source" : "a:2:{i:0;a:0:{}s:2:\"o1\";a:14:{s:8:\"duration\";i:21;s:12:\"content_hash\";s:32:\"cea2646901597d032dc1d7cf9e95f973\";s:12:\"content_type\";s:9:\"video/mp4\";s:9:\"extension\";s:3:\"mp4\";s:5:\"width\";i:640;s:6:\"height\";i:360;s:6:\"aspect\";d:1.7800000000000000266453525910037569701671600341796875;s:15:\"is_video_bucket\";i:1;s:8:\"revision\";i:0;s:18:\"video_preview_size\";s:7:\"200x112\";s:29:\"video_preview_filename_prefix\";s:25:\"tumblr_mzw44qBo0t1qcj5g1_\";s:38:\"video_preview_heywatch_thumbnail_count\";s:2:\"10\";s:17:\"heywatch_video_id\";s:8:\"32124489\";s:27:\"video_preview_filmstrip_url\";s:74:\"http://24.media.tumblr.com/previews/tumblr_mzw44qBo0t1qcj5g1_filmstrip.jpg\";}}",
   "format" : "html",
   "video-caption" : "<p>Literally sparkling garbage bins WHAT</p>",
   "type" : "video",
   "unix-timestamp" : 1390540821
}

