{
   "date-gmt" : "2014-02-01 02:00:21 GMT",
   "mobile" : 0,
   "slug" : "",
   "feed-item" : "",
   "type" : "video",
   "url-with-slug" : "http://tumblr.ggvaidya.com/post/75207730599",
   "video-caption" : "",
   "tags" : [
      "madest thou look",
      "geico",
      "advertisement"
   ],
   "date" : "Fri, 31 Jan 2014 19:00:21",
   "unix-timestamp" : 1391220021,
   "video-source" : "https://www.youtube.com/watch?v=iSxfUmYQeyE",
   "bookmarklet" : 0,
   "from-feed-id" : 0,
   "id" : "75207730599",
   "video-player-500" : false,
   "url" : "http://tumblr.ggvaidya.com/post/75207730599",
   "format" : "html",
   "reblog-key" : "IhOIHyIp",
   "video-player-250" : false,
   "video-player" : false
}

