{
   "date" : "Mon, 28 Apr 2014 18:44:30",
   "reblog-key" : "WYhzmf1C",
   "unix-timestamp" : 1398732270,
   "url" : "http://tumblr.ggvaidya.com/post/84176443214",
   "regular-title" : null,
   "mobile" : 0,
   "from-feed-id" : 0,
   "regular-body" : "<p><a class=\"tumblr_blog\" href=\"http://queerlyobscure.tumblr.com/post/82071636793/yknow-people-say-shit-about-social-media-along\">queerlyobscure</a>:</p>\n<blockquote>\n<p>Y’know people say shit about social media along the lines of ‘OMG no one cares what anyone had for breakfast’ and like.</p>\n<p>I do? I care. I’m pretty sure a lot of people care. I want to hear that the people I care about are having delicious breakfasts or saw something odd at work or flirted with a cute barista. Or just any little thoughts they have that they feel are worth sharing.</p>\n<p>I’ve always kind of assumed that’s how you’re supposed to feel about your friends.</p>\n</blockquote>",
   "slug" : "queerlyobscure-yknow-people-say-shit-about",
   "bookmarklet" : 0,
   "feed-item" : "",
   "tags" : [
      "YES",
      "this",
      "social media"
   ],
   "url-with-slug" : "http://tumblr.ggvaidya.com/post/84176443214/queerlyobscure-yknow-people-say-shit-about",
   "date-gmt" : "2014-04-29 00:44:30 GMT",
   "type" : "regular",
   "format" : "html",
   "id" : "84176443214"
}

