{
   "url" : "http://tumblr.ggvaidya.com/post/86873988559",
   "id" : "86873988559",
   "from-feed-id" : 0,
   "bookmarklet" : 0,
   "regular-title" : "I walked 6.50 kms today",
   "reblog-key" : "a48tzACT",
   "format" : "html",
   "regular-body" : "<p>Whee. Only 5.38 kms were in the <a href=\"http://tumblr.ggvaidya.com/post/86847880189/i-cant-be-seriously-expected-to-work-when-the\">glorious evening we had today</a>, though. But it was all pretty awesome.</p>",
   "type" : "regular",
   "feed-item" : "",
   "slug" : "i-walked-6-50-kms-today",
   "mobile" : 0,
   "date-gmt" : "2014-05-26 06:27:22 GMT",
   "unix-timestamp" : 1401085642,
   "date" : "Mon, 26 May 2014 00:27:22",
   "tags" : [
      "walking",
      "exercise",
      "me"
   ],
   "url-with-slug" : "http://tumblr.ggvaidya.com/post/86873988559/i-walked-6-50-kms-today"
}

