{
   "bookmarklet" : 0,
   "date" : "Fri, 20 Jun 2014 10:39:17",
   "date-gmt" : "2014-06-20 14:39:17 GMT",
   "feed-item" : "",
   "format" : "html",
   "from-feed-id" : 0,
   "id" : "89362286814",
   "is-submission" : false,
   "like-button" : "<div class=\"like_button\" data-post-id=\"89362286814\" data-blog-name=\"mrvaidya\" id=\"like_button_89362286814\"><iframe id=\"like_iframe_89362286814\" src=\"http://assets.tumblr.com/assets/html/like_iframe.html?_v=5716f9145cbbcc5e21aa13229de5d4ed#name=mrvaidya&amp;post_id=89362286814&amp;color=black&amp;rk=dLJQhKjo&amp;root_id=73979447688\" scrolling=\"no\" width=\"20\" height=\"20\" frameborder=\"0\" class=\"like_toggle\" allowTransparency=\"true\" name=\"like_iframe_89362286814\"></iframe></div>",
   "mobile" : 0,
   "note-count" : "470876",
   "reblog-button" : "<a href=\"https://www.tumblr.com/reblog/89362286814/dLJQhKjo\" class=\"reblog_button\"style=\"display: block;width:20px;height:20px;\"><svg width=\"100%\" height=\"100%\" viewBox=\"0 0 21 21\" xmlns=\"http://www.w3.org/2000/svg\" xmlns:xlink=\"http://www.w3.org/1999/xlink\" fill=\"#000\"><path d=\"M5.01092527,5.99908429 L16.0088498,5.99908429 L16.136,9.508 L20.836,4.752 L16.136,0.083 L16.1360004,3.01110845 L2.09985349,3.01110845 C1.50585349,3.01110845 0.979248041,3.44726568 0.979248041,4.45007306 L0.979248041,10.9999998 L3.98376463,8.30993634 L3.98376463,6.89801007 C3.98376463,6.20867902 4.71892527,5.99908429 5.01092527,5.99908429 Z\"></path><path d=\"M17.1420002,13.2800293 C17.1420002,13.5720293 17.022957,14.0490723 16.730957,14.0490723 L4.92919922,14.0490723 L4.92919922,11 L0.5,15.806 L4.92919922,20.5103758 L5.00469971,16.9990234 L18.9700928,16.9990234 C19.5640928,16.9990234 19.9453125,16.4010001 19.9453125,15.8060001 L19.9453125,9.5324707 L17.142,12.203\"></path></svg></a>",
   "reblog-key" : "dLJQhKjo",
   "reblogged-from-name" : "natattacker",
   "reblogged-from-title" : "Back the fuck up, you soggy lampshade",
   "reblogged-from-url" : "https://natattacker.tumblr.com/post/89361106027/juli-the-human-shubbabang-you-know-that",
   "reblogged-root-name" : "shubbabang",
   "reblogged-root-title" : "welcome to thunderdome",
   "reblogged-root-url" : "http://shubbabang.tumblr.com/post/73979447688/you-know-that-thing-where-you-scrunch-up-your-arms",
   "reblogged_from_avatar_url_128" : "http://68.media.tumblr.com/avatar_c244701f3b97_128.png",
   "reblogged_from_avatar_url_16" : "http://68.media.tumblr.com/avatar_c244701f3b97_16.png",
   "reblogged_from_avatar_url_24" : "http://68.media.tumblr.com/avatar_c244701f3b97_24.png",
   "reblogged_from_avatar_url_30" : "http://68.media.tumblr.com/avatar_c244701f3b97_30.png",
   "reblogged_from_avatar_url_40" : "http://68.media.tumblr.com/avatar_c244701f3b97_40.png",
   "reblogged_from_avatar_url_48" : "http://68.media.tumblr.com/avatar_c244701f3b97_48.png",
   "reblogged_from_avatar_url_512" : "http://68.media.tumblr.com/avatar_c244701f3b97_512.png",
   "reblogged_from_avatar_url_64" : "http://68.media.tumblr.com/avatar_c244701f3b97_64.png",
   "reblogged_from_avatar_url_96" : "http://68.media.tumblr.com/avatar_c244701f3b97_96.png",
   "reblogged_root_avatar_url_128" : "http://68.media.tumblr.com/avatar_8ee6b7289dba_128.png",
   "reblogged_root_avatar_url_16" : "http://68.media.tumblr.com/avatar_8ee6b7289dba_16.png",
   "reblogged_root_avatar_url_24" : "http://68.media.tumblr.com/avatar_8ee6b7289dba_24.png",
   "reblogged_root_avatar_url_30" : "http://68.media.tumblr.com/avatar_8ee6b7289dba_30.png",
   "reblogged_root_avatar_url_40" : "http://68.media.tumblr.com/avatar_8ee6b7289dba_40.png",
   "reblogged_root_avatar_url_48" : "http://68.media.tumblr.com/avatar_8ee6b7289dba_48.png",
   "reblogged_root_avatar_url_512" : "http://68.media.tumblr.com/avatar_8ee6b7289dba_512.png",
   "reblogged_root_avatar_url_64" : "http://68.media.tumblr.com/avatar_8ee6b7289dba_64.png",
   "reblogged_root_avatar_url_96" : "http://68.media.tumblr.com/avatar_8ee6b7289dba_96.png",
   "regular-body" : "<p><a class=\"tumblr_blog\" href=\"http://juli-the-human.tumblr.com/post/74002293899/shubbabang-you-know-that-thing-where-you\">juli-the-human</a>:</p>\n<blockquote>\n<p><a class=\"tumblr_blog\" href=\"http://shubbabang.tumblr.com/post/73979447688/you-know-that-thing-where-you-scrunch-up-your-arms\">shubbabang</a>:</p>\n<blockquote>\n<p>you know that thing where you scrunch up your arms and it looks like you have only hands well this one time when i was little i kept it up for 3 days no matter where i was</p>\n<p><img alt=\"image\" src=\"http://68.media.tumblr.com/d5ce64f1cec336a7b8f82a72e8ea7012/tumblr_inline_mzpu6tRxkz1qm8np9.png\"/></p>\n<p><img alt=\"image\" src=\"http://68.media.tumblr.com/7fd53862fda5c0149ac481aadec562cf/tumblr_inline_mzpuqgMVcJ1qm8np9.png\"/></p>\n<p><img alt=\"image\" src=\"http://68.media.tumblr.com/07edca7c8856292d36ae882e438df59b/tumblr_inline_mzpuqscsxR1qm8np9.png\"/></p>\n<p><img alt=\"image\" src=\"http://68.media.tumblr.com/86eaa9bef05a26170e87d29f65d04347/tumblr_inline_mzputyDZpK1qm8np9.png\"/></p>\n<p><img alt=\"image\" src=\"http://68.media.tumblr.com/78ee711212a5fabf9ef6a627e4bf3e7c/tumblr_inline_mzpuu5mwlY1qm8np9.png\"/></p>\n<p><img alt=\"image\" src=\"http://68.media.tumblr.com/736eb8dcfd6d767c079de41d1663ac9e/tumblr_inline_mzpuurwxxP1qm8np9.png\"/></p>\n<p><img alt=\"image\" src=\"http://68.media.tumblr.com/5d06566c9657d21bc2a3edb552e41ea8/tumblr_inline_mzpuv1srbI1qm8np9.png\"/></p>\n<p><img alt=\"image\" src=\"http://68.media.tumblr.com/4a03cf637635c7c1abee813ce1c2bf47/tumblr_inline_mzpuv7PHIb1qm8np9.png\"/></p>\n<p><img alt=\"image\" src=\"http://68.media.tumblr.com/a1370b7346bcb094ce647a9f7f4b22cd/tumblr_inline_mzpuvehVW11qm8np9.png\"/></p>\n<p>one time i also pissed off my entire family for 3 days</p>\n</blockquote>\n<p><strong>the last picture i cANT <em>BREATHE</em></strong></p>\n</blockquote>",
   "regular-title" : null,
   "slug" : "juli-the-human-shubbabang-you-know-that",
   "tags" : [
      "children"
   ],
   "tumblelog" : {
      "avatar_url_128" : "http://68.media.tumblr.com/avatar_d75db498370e_128.png",
      "avatar_url_16" : "http://68.media.tumblr.com/avatar_d75db498370e_16.png",
      "avatar_url_24" : "http://68.media.tumblr.com/avatar_d75db498370e_24.png",
      "avatar_url_30" : "http://68.media.tumblr.com/avatar_d75db498370e_30.png",
      "avatar_url_40" : "http://68.media.tumblr.com/avatar_d75db498370e_40.png",
      "avatar_url_48" : "http://68.media.tumblr.com/avatar_d75db498370e_48.png",
      "avatar_url_512" : "http://68.media.tumblr.com/avatar_d75db498370e_512.png",
      "avatar_url_64" : "http://68.media.tumblr.com/avatar_d75db498370e_64.png",
      "avatar_url_96" : "http://68.media.tumblr.com/avatar_d75db498370e_96.png",
      "cname" : "tumblr.ggvaidya.com",
      "name" : "mrvaidya",
      "timezone" : "US/Eastern",
      "title" : "Gaurav's Tumblr",
      "url" : "http://tumblr.ggvaidya.com/"
   },
   "type" : "regular",
   "unix-timestamp" : 1403275157,
   "url" : "http://tumblr.ggvaidya.com/post/89362286814",
   "url-with-slug" : "http://tumblr.ggvaidya.com/post/89362286814/juli-the-human-shubbabang-you-know-that"
}

