{
   "bookmarklet" : 0,
   "date" : "Sun, 27 Jul 2014 13:30:49",
   "date-gmt" : "2014-07-27 19:30:49 GMT",
   "feed-item" : "",
   "format" : "html",
   "from-feed-id" : 0,
   "height" : 1681,
   "id" : "93035716419",
   "mobile" : 0,
   "photo-caption" : "<p><a href=\"http://erikkwakkel.tumblr.com/post/93034498611/funny-rabbits-i-just-encountered-this-clever-and\" class=\"tumblr_blog\">erikkwakkel</a>:</p>\n\n<blockquote><p><strong>Funny rabbits</strong></p>\n<p>I just encountered this clever and amusing image in a <span>French </span><span>database of medieval manuscripts. It shows three rabbits running in circles - with shared ears. There is nothing much to this drawing from a book-historical point of view, except to say that it has an Escher-feel to it. In fact, I am not even sure what it means to convey. I am simply sharing it here because the ear entanglement is so cleverly done - and the whole scene brought a big smile to my face.</span></p>\n<p><span>Pic: Arras, Bibliothèque municipale, MS 7 (13th century).</span></p></blockquote>",
   "photo-url-100" : "http://66.media.tumblr.com/475112ff69ec6556bfbd5d764048f69c/tumblr_n9dx54CWIN1soj7s4o1_100.jpg",
   "photo-url-1280" : "http://40.media.tumblr.com/475112ff69ec6556bfbd5d764048f69c/tumblr_n9dx54CWIN1soj7s4o1_1280.jpg",
   "photo-url-250" : "http://41.media.tumblr.com/475112ff69ec6556bfbd5d764048f69c/tumblr_n9dx54CWIN1soj7s4o1_250.jpg",
   "photo-url-400" : "http://65.media.tumblr.com/475112ff69ec6556bfbd5d764048f69c/tumblr_n9dx54CWIN1soj7s4o1_400.jpg",
   "photo-url-500" : "http://65.media.tumblr.com/475112ff69ec6556bfbd5d764048f69c/tumblr_n9dx54CWIN1soj7s4o1_500.jpg",
   "photo-url-75" : "http://36.media.tumblr.com/475112ff69ec6556bfbd5d764048f69c/tumblr_n9dx54CWIN1soj7s4o1_75sq.jpg",
   "photos" : [],
   "reblog-key" : "D6yu4x8j",
   "slug" : "erikkwakkel-funny-rabbits-i-just-encountered",
   "tags" : [
      "hee",
      "rabbits"
   ],
   "type" : "photo",
   "unix-timestamp" : 1406489449,
   "url" : "http://tumblr.ggvaidya.com/post/93035716419",
   "url-with-slug" : "http://tumblr.ggvaidya.com/post/93035716419/erikkwakkel-funny-rabbits-i-just-encountered",
   "width" : 1642
}

